my_own_package/__init__.py
Mariana_first_package-0.1.0.dist-info/METADATA
Mariana_first_package-0.1.0.dist-info/WHEEL
Mariana_first_package-0.1.0.dist-info/top_level.txt
Mariana_first_package-0.1.0.dist-info/RECORD
