Metadata-Version: 2.1
Name: Mariana-first-package
Version: 0.1.0
Summary: This is my first time when I made my own package
Author: Mariana Balan
Author-email: marianabalan78@yahoo.com
